MANIFEST.in
README.md
grayscale_image.py
requirements.txt
setup.py
grayscale_image.egg-info/PKG-INFO
grayscale_image.egg-info/SOURCES.txt
grayscale_image.egg-info/dependency_links.txt
grayscale_image.egg-info/entry_points.txt
grayscale_image.egg-info/not-zip-safe
grayscale_image.egg-info/requires.txt
grayscale_image.egg-info/top_level.txt